processador_de_imagem/__init__.py
processador_de_imagem/processando/__init__.py
processador_de_imagem/processando/combinacao.py
processador_de_imagem/processando/transformacao.py
processador_de_imagem/util/__init__.py
processador_de_imagem/util/io.py
processador_de_imagem/util/plot.py
Processador_de_imagem-0.0.1.dist-info/METADATA
Processador_de_imagem-0.0.1.dist-info/WHEEL
Processador_de_imagem-0.0.1.dist-info/top_level.txt
Processador_de_imagem-0.0.1.dist-info/RECORD
