Metadata-Version: 2.1
Name: Processador-de-imagem
Version: 0.0.1
Summary: Pacote de processamento de imagem usando Skimage
Home-page: https://github.com/prikrdo/processador_de_imagem
Author: Paulo Silva
Author-email: paulo_rikrdo@hotmail.com
Requires-Python: >=3.8
Requires-Dist: matplotlib
Requires-Dist: numpy
Requires-Dist: scikit-image (>=0.16.1)
